makemake/__init__.py
makemake/makemake.py
makemake-0.2.data/scripts/makemake
makemake-0.2.dist-info/LICENSE
makemake-0.2.dist-info/METADATA
makemake-0.2.dist-info/WHEEL
makemake-0.2.dist-info/top_level.txt
makemake-0.2.dist-info/RECORD
