Metadata-Version: 2.1
Name: makemake
Version: 0.2
Summary: A simple makefile generator for C projects
Home-page: https://github.com/andreas-schwenk/makemake
Author: Andreas Schwenk
Author-email: contact@compiler-construction.com
License: GPLv3
Keywords: make makefile C build
Classifier: Development Status :: 4 - Beta
Classifier: Intended Audience :: Developers
Classifier: Topic :: Software Development :: Build Tools
Classifier: License :: OSI Approved :: GNU General Public License v3 (GPLv3)
Classifier: Programming Language :: Python :: 3.9
License-File: LICENSE
